dnnv/__init__.py
dnnv/__main__.py
dnnv/__version__.py
dnnv/errors.py
dnnv/utils.py
dnnv/_manage/__init__.py
dnnv/_manage/__main__.py
dnnv/_manage/errors.py
dnnv/_manage/linux/__init__.py
dnnv/_manage/linux/environment/__init__.py
dnnv/_manage/linux/environment/base.py
dnnv/_manage/linux/environment/dependencies/__init__.py
dnnv/_manage/linux/environment/dependencies/base.py
dnnv/_manage/linux/environment/dependencies/installers/__init__.py
dnnv/_manage/linux/environment/dependencies/installers/base.py
dnnv/_manage/linux/environment/dependencies/installers/common.py
dnnv/_manage/linux/verifiers/__init__.py
dnnv/_manage/linux/verifiers/bab.py
dnnv/_manage/linux/verifiers/babsb.py
dnnv/_manage/linux/verifiers/eran.py
dnnv/_manage/linux/verifiers/marabou.py
dnnv/_manage/linux/verifiers/mipverify.py
dnnv/_manage/linux/verifiers/neurify.py
dnnv/_manage/linux/verifiers/nnenum.py
dnnv/_manage/linux/verifiers/planet.py
dnnv/_manage/linux/verifiers/reluplex.py
dnnv/_manage/linux/verifiers/verinet.py
dnnv/cli/__init__.py
dnnv/logging_utils/__init__.py
dnnv/nn/__init__.py
dnnv/nn/graph.py
dnnv/nn/utils.py
dnnv/nn/visitors.py
dnnv/nn/analyzers/__init__.py
dnnv/nn/analyzers/base.py
dnnv/nn/converters/__init__.py
dnnv/nn/converters/onnx.py
dnnv/nn/converters/tensorflow.py
dnnv/nn/layers/__init__.py
dnnv/nn/layers/base.py
dnnv/nn/operations/__init__.py
dnnv/nn/operations/base.py
dnnv/nn/operations/generator.py
dnnv/nn/operations/math.py
dnnv/nn/operations/nn.py
dnnv/nn/operations/patterns.py
dnnv/nn/operations/tensor.py
dnnv/nn/parser/__init__.py
dnnv/nn/parser/onnx.py
dnnv/nn/transformers/__init__.py
dnnv/nn/transformers/base.py
dnnv/nn/transformers/slicers.py
dnnv/nn/transformers/simplifiers/__init__.py
dnnv/nn/transformers/simplifiers/base.py
dnnv/nn/transformers/simplifiers/bundle_padding.py
dnnv/nn/transformers/simplifiers/bundle_transpose.py
dnnv/nn/transformers/simplifiers/convert_add.py
dnnv/nn/transformers/simplifiers/convert_batch_norm.py
dnnv-0.6.0.dist-info/entry_points.txt
dnnv-0.6.0.dist-info/LICENSE
dnnv-0.6.0.dist-info/WHEEL
dnnv-0.6.0.dist-info/METADATA
dnnv-0.6.0.dist-info/RECORD
