Metadata-Version: 2.1
Name: dnnv
Version: 0.6.0
Summary: dnnv - deep neural network verification
Keywords: DNN,neural network,verification
Author-email: David Shriver <dls2fc@virginia.edu>
Requires-Python: >=3.7
Classifier: License :: OSI Approved :: MIT License
Requires-Dist: lark~=1.0
Requires-Dist: numpy>=1.20,<1.22
Requires-Dist: onnx>=1.8,<1.11
Requires-Dist: onnxruntime~=1.8
Requires-Dist: psutil~=5.6
Requires-Dist: scikit-image>=0.18,<0.19
Requires-Dist: scipy~=1.7
Requires-Dist: tensorflow>=2.2,<2.8
Requires-Dist: lark~=1.0 ; extra == "all"
Requires-Dist: numpy>=1.20,<1.22 ; extra == "all"
Requires-Dist: onnx>=1.8,<1.11 ; extra == "all"
Requires-Dist: psutil~=5.6 ; extra == "all"
Requires-Dist: scikit-image>=0.18,<0.19 ; extra == "all"
Requires-Dist: scipy~=1.7 ; extra == "all"
Requires-Dist: tensorflow>=2.2,<2.8 ; extra == "all"
Requires-Dist: coverage~=5.5 ; extra == "all"
Requires-Dist: pytest~=6.2 ; extra == "all"
Requires-Dist: torch~=1.5 ; extra == "all"
Requires-Dist: torchvision~=0.6 ; extra == "all"
Requires-Dist: black~=22.3 ; extra == "all"
Requires-Dist: isort~=5.10 ; extra == "all"
Requires-Dist: mypy~=0.942 ; extra == "all"
Requires-Dist: sphinx ; extra == "all"
Requires-Dist: furo ; extra == "all"
Requires-Dist: black~=22.3 ; extra == "dev"
Requires-Dist: isort~=5.10 ; extra == "dev"
Requires-Dist: mypy~=0.942 ; extra == "dev"
Requires-Dist: sphinx ; extra == "docs"
Requires-Dist: furo ; extra == "docs"
Requires-Dist: coverage~=5.5 ; extra == "test"
Requires-Dist: pytest~=6.2 ; extra == "test"
Requires-Dist: torch~=1.5 ; extra == "test"
Requires-Dist: torchvision~=0.6 ; extra == "test"
Project-URL: Documentation, https://dnnv.readthedocs.io/en/latest/
Project-URL: Source, https://github.com/dlshriver/dnnv
Provides-Extra: all
Provides-Extra: dev
Provides-Extra: docs
Provides-Extra: test
